[{"de":"vendedor1","fecha":"2026-05-23","mensaje":"Puede_visitarla_el_sabado_a_las_10am","para":"cliente1","propiedad_id":"prop001"},{"de":"cliente1","fecha":"2026-05-23","mensaje":"Hola_me_interesa_la_propiedad_cuando_puedo_visitarla  Esperado en T2: Mensaje enviado. El propietario será notificado.","para":"vendedor1","propiedad_id":"prop001"},{"de":"cliente2","fecha":"2026-05-23","mensaje":"Prueba1","para":"vendedor1","propiedad_id":"prop001"},{"de":"cliente1","fecha":"2026-05-23","mensaje":"Prueba0","para":"vendedor1","propiedad_id":"prop002"},{"de":"cliente1","fecha":"2026-05-23","mensaje":"hola","para":"vendedor1","propiedad_id":"prop001"},{"de":"cliente1","fecha":"2026-05-23","mensaje":"hola","para":"vendedor1","propiedad_id":"prop001"},{"de":"cliente1","fecha":"2026-05-23","mensaje":"Hola","para":"vendedor1","propiedad_id":"prop001"},{"de":"vendedor1","fecha":"2026-05-21","mensaje":"Adios","para":"cliente1","propiedad_id":"prop001"},{"de":"cliente1","fecha":"2026-05-21","mensaje":"Hola","para":"vendedor1","propiedad_id":"prop001"},{"de":"vendedor1","fecha":"2026-05-21","mensaje":"Claro,_puedes_visitarla_el_sabado_a_las_10am","para":"cliente1","propiedad_id":"prop001"},{"de":"cliente1","fecha":"2026-05-21","mensaje":"Hola vendedor me interesa","para":"vendedor1","propiedad_id":"prop001"}]